README.md
setup.py
cleandev_resp_builder.egg-info/PKG-INFO
cleandev_resp_builder.egg-info/SOURCES.txt
cleandev_resp_builder.egg-info/dependency_links.txt
cleandev_resp_builder.egg-info/requires.txt
cleandev_resp_builder.egg-info/top_level.txt
resp_builder/__init__.py
resp_builder/config.py
resp_builder/inmutables.py
resp_builder/interfaces.py