Metadata-Version: 2.1
Name: cleandev-resp-builder
Version: 0.2.1
Summary: Module for handler errors codes in your APIS
Home-page: https://gitlab.com/cleansoftware/libs/public/cleandev-resp-builder
Author: Daniel Rodriguez Rodriguez
Author-email: danielrodriguezrodriguez.pks@gmail.com
License: UNKNOWN
Project-URL: Bug Tracker, https://gitlab.com/cleansoftware/libs/public/cleandev-resp-builder/-/issues
Platform: UNKNOWN
Classifier: Programming Language :: Python :: 3
Classifier: License :: OSI Approved :: MIT License
Classifier: Operating System :: OS Independent
Requires-Python: >=3.9
